simpleArgParser/__init__.py
simpleArgParser/s_argparse.py
simpleargparser-0.1.9.dist-info/METADATA
simpleargparser-0.1.9.dist-info/WHEEL
simpleargparser-0.1.9.dist-info/top_level.txt
simpleargparser-0.1.9.dist-info/RECORD
