Metadata-Version: 2.4
Name: simpleArgParser
Version: 0.1.9
Summary: A simple typed argument parser using dataclasses and type hints. This project is largely generated by ChatGPT.
Home-page: https://github.com/Raibows/SimpleArgParser
Author: raibows
Author-email: raibows@hotmail.com
Classifier: Programming Language :: Python :: 3
Classifier: License :: OSI Approved :: MIT License
Requires-Python: >=3.8
Dynamic: author
Dynamic: author-email
Dynamic: classifier
Dynamic: description
Dynamic: description-content-type
Dynamic: home-page
Dynamic: requires-python
Dynamic: summary
